edtf_validate/__init__.py
edtf_validate/valid_edtf.py
edtf_validate-2.0.0.dist-info/LICENSE.txt
edtf_validate-2.0.0.dist-info/METADATA
edtf_validate-2.0.0.dist-info/WHEEL
edtf_validate-2.0.0.dist-info/entry_points.txt
edtf_validate-2.0.0.dist-info/top_level.txt
edtf_validate-2.0.0.dist-info/RECORD
